table_generator/__init__.py
table_generator-0.0.3.dist-info/LICENSE.txt
table_generator-0.0.3.dist-info/METADATA
table_generator-0.0.3.dist-info/WHEEL
table_generator-0.0.3.dist-info/top_level.txt
table_generator-0.0.3.dist-info/RECORD
