Metadata-Version: 2.1
Name: table-generator
Version: 0.0.3
Summary: Generates code for html table from csv files
Home-page: https://github.com/lol-cubes/table_generator
Author: Arin Khare
Author-email: arinmkhare@gmail.com
License: UNKNOWN
Platform: UNKNOWN
Classifier: Programming Language :: Python :: 3
Classifier: License :: OSI Approved :: MIT License
Classifier: Operating System :: MacOS :: MacOS X
Requires-Dist: lxml
